LICENSE
README.md
setup.py
pynettool/__init__.py
pynettool/__main__.py
pynettool/pyping.py
pynettool/setup.py
pynettool.egg-info/PKG-INFO
pynettool.egg-info/SOURCES.txt
pynettool.egg-info/dependency_links.txt
pynettool.egg-info/requires.txt
pynettool.egg-info/top_level.txt