Metadata-Version: 2.2
Name: pynettool
Version: 1.0
Summary: pynettool: A command line tool that displays information about the Internet connection of current system
Home-page: http://blog.cycleuser.org
Author: cycleuser
Author-email: cycleuser@cycleuser.org
License-File: LICENSE
Requires-Dist: speedtest-cli
Requires-Dist: tabulate
Requires-Dist: requests
Requires-Dist: distro
Dynamic: author
Dynamic: author-email
Dynamic: description
Dynamic: description-content-type
Dynamic: home-page
Dynamic: requires-dist
Dynamic: summary
